MANIFEST.in
README.rst
setup.py
R_buildtest_config.egg-info/PKG-INFO
R_buildtest_config.egg-info/SOURCES.txt
R_buildtest_config.egg-info/dependency_links.txt
R_buildtest_config.egg-info/requires.txt
R_buildtest_config.egg-info/top_level.txt
buildtest/__init__.py
buildtest/R/code/ADGofTest/ad.test.R
buildtest/R/code/ADGofTest/reference.txt
buildtest/R/code/AUC/AUC-package.R
buildtest/R/code/AUC/Rplots.pdf
buildtest/R/code/AUC/accuracy.R
buildtest/R/code/AUC/auc.R
buildtest/R/code/AUC/churn.R
buildtest/R/code/AUC/plot.AUC.R
buildtest/R/code/AUC/reference.txt
buildtest/R/code/AUC/roc.R
buildtest/R/code/AUC/sensitivity.R
buildtest/R/code/AUC/specificity.R
buildtest/R/code/AlgDesign/gen.factorial.R
buildtest/R/code/AlgDesign/optBlock.R
buildtest/R/code/AlgDesign/optFederov.R
buildtest/R/code/AlgDesign/optMonteCarlo.R
buildtest/R/code/AlgDesign/reference.txt
buildtest/R/code/BatchJobs/batchExpandGrid.R
buildtest/R/code/BatchJobs/batchMap.R
buildtest/R/code/BatchJobs/batchMapResults.R
buildtest/R/code/BatchJobs/batchReduce.R
buildtest/R/code/BatchJobs/batchReduceResults.R
buildtest/R/code/BatchJobs/filterResults.R
buildtest/R/code/BatchJobs/findJobs.R
buildtest/R/code/BatchJobs/killJobs.R
buildtest/R/code/BatchJobs/makeClusterFunctionsSSH.R
buildtest/R/code/BatchJobs/makeRegistry.R
buildtest/R/code/BatchJobs/reduceResults.R
buildtest/R/code/BatchJobs/reference.txt
buildtest/R/code/BatchJobs/showStatus.R
buildtest/R/code/BatchJobs/submitJobs.R
buildtest/R/code/BatchJobs/testJob.R
buildtest/R/code/Brobdingnag/as.brob.R
buildtest/R/code/Brobdingnag/reference.txt
buildtest/R/code/Cairo/Cairo.onSave.R
buildtest/R/code/Cairo/reference.txt
buildtest/R/code/EasyABC/EasyABC.R
buildtest/R/code/EasyABC/reference.txt
buildtest/R/code/FME/FME.R
buildtest/R/code/FME/Rplots.pdf
buildtest/R/code/FNN/FNN.R
buildtest/R/code/FactoMineR/FactoMineR.R
buildtest/R/code/FactoMineR/reference.txt
buildtest/R/code/Formula/Formula.R
buildtest/R/code/SuperLearner/create.Learner.R
buildtest/R/code/SuperLearner/reference.txt
buildtest/R/code/SuppDists/Rplots.pdf
buildtest/R/code/SuppDists/pFriedman.R
buildtest/R/code/SuppDists/reference.txt
buildtest/R/code/TH.data/GBSG2.R
buildtest/R/code/TH.data/Westbc.R
